{
  "key": "KR",
  "label": "대한민국 (Republic of Korea)",
  "review_status": "DRAFT — requires review by a qualified Korean entertainment lawyer",
  "sources_as_of": "2026-06",
  "issues": [
    {
      "topic": "저작권 / 저작인접권",
      "law": "저작권법 (Copyright Act)",
      "note": "실연자·음반제작자의 저작인접권, 2차적저작물작성권, 양도 범위와 존속기간. AI 학습용 복제·전송 권리가 양도 범위에 포함되는지 명시 필요."
    },
    {
      "topic": "전속계약 공정성",
      "law": "공정거래법 / 공정위 대중문화예술인 표준전속계약서",
      "note": "전속 기간, 수익 배분, 위약벌·해지 조항의 불공정성 심사. 표준계약서 대비 과도한 구속은 무효 가능."
    },
    {
      "topic": "약관의 공정성",
      "law": "약관의 규제에 관한 법률 (약관규제법)",
      "note": "사업자가 일방적으로 정한 정형 약관 중 고객에게 부당하게 불리한 조항(무제한·무기한 권리 부여 등)은 무효."
    },
    {
      "topic": "초상·음성 / 퍼블리시티",
      "law": "부정경쟁방지 및 영업비밀보호에 관한 법률 (개정, 데이터·성과물 보호)",
      "note": "타인의 초상·음성 등 인적 식별표지의 무단 이용 규율. AI 음성 복제·합성 커버 관련 국내 논의 진행 중."
    },
    {
      "topic": "신탁관리 / 권리 처리",
      "law": "저작권법상 신탁관리(KOMCA, 함께하는음악저작인협회 등)",
      "note": "신탁된 권리는 개별 계약으로 임의 처분 불가. AI 이용 허락의 주체·범위 확인 필요."
    },
    {
      "topic": "AI 합성·딥보이스",
      "law": "정보통신망법 / 개정 입법 논의",
      "note": "음성 합성·딥페이크 관련 규율은 발전 중. 계약상 명시적 동의·철회권·용도 제한이 핵심."
    }
  ],
  "prompt_context": "준거 관할: 대한민국. 다음 한국 법리를 우선 적용하라 — 저작권법(저작인접권/양도 범위/존속기간), 공정거래법 및 공정위 대중문화예술인 표준전속계약서(전속 기간·수익배분·위약벌의 공정성), 약관규제법(무기한·무제한 권리 부여 등 불공정 약관의 무효 가능성), 부정경쟁방지법 개정(초상·음성 등 인적 식별표지 보호), 신탁관리(KOMCA 등 신탁 권리의 임의 처분 제한). AI 음성 복제·합성 커버에 대한 명시적 동의·용도 제한·철회권의 유무를 반드시 평가하라."
}
